.DS_Store
django_permalinker/__init__.py
django_permalinker/admin.py
django_permalinker/apps.py
django_permalinker/exceptions.py
django_permalinker/models.py
django_permalinker/settings.py
django_permalinker/tests.py
django_permalinker/urls.py
django_permalinker/views.py
django_permalinker/migrations/0001_initial.py
django_permalinker/migrations/__init__.py
django_permalinker-0.1.1.dist-info/LICENSE
django_permalinker-0.1.1.dist-info/METADATA
django_permalinker-0.1.1.dist-info/WHEEL
django_permalinker-0.1.1.dist-info/top_level.txt
django_permalinker-0.1.1.dist-info/RECORD
