Metadata-Version: 2.1
Name: django-permalinker
Version: 0.1.1
Summary: Django application to create, manage, and redirect permanent links
Home-page: https://github.com/efficient-solutions/django-permalinker
Author: Efficient Solutions LLC
Author-email: contact@efficient.solutions
License: MIT
Keywords: Django,Permanent links,Permalinks,URL Shortener
Classifier: Intended Audience :: Developers
Classifier: Natural Language :: English
Classifier: License :: OSI Approved :: MIT License
Classifier: Programming Language :: Python
Classifier: Programming Language :: Python :: 3
Classifier: Programming Language :: Python :: 3 :: Only
Classifier: Programming Language :: Python :: 3.10
Classifier: Programming Language :: Python :: 3.11
Classifier: Programming Language :: Python :: 3.12
Requires-Python: >= 3.10
License-File: LICENSE
Requires-Dist: Django <6,>=4
